instill/__init__.py
instill/__main__.py
instill/clients/__init__.py
instill/clients/artifact.py
instill/clients/base.py
instill/clients/client.py
instill/clients/instance.py
instill/clients/mgmt.py
instill/clients/model.py
instill/clients/pipeline.py
instill/config/__init__.py
instill/helpers/__init__.py
instill/helpers/cli.py
instill/helpers/commands/__init__.py
instill/helpers/commands/build.py
instill/helpers/commands/init.py
instill/helpers/commands/push.py
instill/helpers/commands/run.py
instill/helpers/commands/utils.py
instill/helpers/const.py
instill/helpers/docker/.dockerignore
instill/helpers/docker/Dockerfile
instill/helpers/docker/Dockerfile.mlc-llm
instill/helpers/docker/Dockerfile.transformers
instill/helpers/docker/Dockerfile.vllm
instill/helpers/errors.py
instill/helpers/init-templates/instill.yaml
instill/helpers/init-templates/model.py
instill/helpers/ray_config.py
instill/helpers/ray_io.py
instill/helpers/utils.py
instill/protogen/.git
instill/protogen/.github/CODEOWNERS
instill/protogen/.github/workflows/releases.yml
instill/protogen/CHANGELOG.md
instill/protogen/LICENSE
instill/protogen/README.md
instill/protogen/agent/agent/v1alpha/agent_pb2.py
instill/protogen/agent/agent/v1alpha/agent_pb2.pyi
instill/protogen/agent/agent/v1alpha/agent_pb2_grpc.py
instill/protogen/agent/agent/v1alpha/agent_pb2_grpc.pyi
instill/protogen/agent/agent/v1alpha/agent_public_service_pb2.py
instill/protogen/agent/agent/v1alpha/agent_public_service_pb2.pyi
instill/protogen/agent/agent/v1alpha/agent_public_service_pb2_grpc.py
instill/protogen/agent/agent/v1alpha/agent_public_service_pb2_grpc.pyi
instill/protogen/agent/agent/v1alpha/chat_pb2.py
instill/protogen/agent/agent/v1alpha/chat_pb2.pyi
instill/protogen/agent/agent/v1alpha/chat_pb2_grpc.py
instill/protogen/agent/agent/v1alpha/chat_pb2_grpc.pyi
instill/protogen/agent/agent/v1alpha/common_pb2.py
instill/protogen/agent/agent/v1alpha/common_pb2.pyi
instill/protogen/agent/agent/v1alpha/common_pb2_grpc.py
instill_sdk-0.18.0.dist-info/LICENSE.md
instill_sdk-0.18.0.dist-info/METADATA
instill_sdk-0.18.0.dist-info/WHEEL
instill_sdk-0.18.0.dist-info/entry_points.txt
instill_sdk-0.18.0.dist-info/RECORD
