Metadata-Version: 2.3
Name: instill-sdk
Version: 0.18.0
Summary: python sdk for Instill AI products
License: MIT
Author: instill-ai
Author-email: drop@instill-ai.com
Maintainer: Ping-Lin Chang
Maintainer-email: ping-lin.chang@instill-ai.com
Requires-Python: >=3.9,<3.13
Classifier: Development Status :: 1 - Planning
Classifier: License :: OSI Approved :: MIT License
Classifier: Natural Language :: English
Classifier: Operating System :: OS Independent
Classifier: Programming Language :: Python :: 3
Classifier: Programming Language :: Python :: 3.9
Classifier: Programming Language :: Python :: 3.10
Classifier: Programming Language :: Python :: 3.11
Classifier: Programming Language :: Python :: 3.12
Classifier: Programming Language :: Python :: 3.8
Requires-Dist: fastapi (>=0.115.12,<0.116.0)
Requires-Dist: google-api-core (>=2.11.1,<3.0.0)
Requires-Dist: googleapis-common-protos (>=1.60.0,<2.0.0)
Requires-Dist: grpcio (>=1.59.0,<2.0.0)
Requires-Dist: jsonschema (>=4.20.0,<5.0.0)
Requires-Dist: numpy (>=1.21.0,<2.0.0)
Requires-Dist: pillow (>=10.1.0,<11.0.0)
Requires-Dist: pkginfo (>=1.12.1.2,<2.0.0.0)
Requires-Dist: protobuf (==4.25.8)
Requires-Dist: protoc-gen-openapiv2 (>=0.0.1,<0.0.2)
Requires-Dist: pydantic (>=1.10.13)
Requires-Dist: pyyaml (>=6.0.1,<7.0.0)
Requires-Dist: ray (==2.47.0)
Requires-Dist: requests (==2.32.3)
Requires-Dist: starlette (>=0.46.1,<0.47.0)
Requires-Dist: types-protobuf (>=4.24.0.1,<5.0.0.0)
Requires-Dist: types-pyyaml (>=6.0.12.11,<7.0.0.0)
Requires-Dist: types-requests (==2.31.0.6)
Requires-Dist: urllib3 (==1.26.20)
Requires-Dist: uvicorn (>=0.34.0,<0.35.0)
Requires-Dist: virtualenv (>=20.30.0,<21.0.0)
Project-URL: Documentation, https://instill-sdk.readthedocs.io
Project-URL: Homepage, https://pypi.org/project/instill-sdk
Project-URL: Repository, https://github.com/instill-ai/python-sdk
